ease_mailer/__init__.py
ease_mailer/mailer.py
ease_mailer-1.2.dist-info/LICENSE.txt
ease_mailer-1.2.dist-info/METADATA
ease_mailer-1.2.dist-info/WHEEL
ease_mailer-1.2.dist-info/top_level.txt
ease_mailer-1.2.dist-info/RECORD
