Metadata-Version: 2.1
Name: ease-mailer
Version: 1.2
Summary: ease_mailer is the easiest way for email sending.
Home-page: UNKNOWN
Author: Tech Smit
Author-email: techsmitdevloper@gmail.com
License: MIT
Keywords: Email Sending,Send Mail,Easy Email Sender,Send Multiple Mail
Platform: UNKNOWN
Classifier: Development Status :: 3 - Alpha
Classifier: Intended Audience :: Developers
Classifier: Topic :: Software Development :: Build Tools
Classifier: License :: OSI Approved :: MIT License
Classifier: Programming Language :: Python :: 3
License-File: LICENSE.txt
